vela/__init__.py
vela-0.0.13.dist-info/LICENSE
vela-0.0.13.dist-info/METADATA
vela-0.0.13.dist-info/WHEEL
vela-0.0.13.dist-info/top_level.txt
vela-0.0.13.dist-info/RECORD
