Metadata-Version: 2.1
Name: vela
Version: 0.0.13
Summary: A simple framework for Gemini servers inspired by Flask and Express.js.
Home-page: https://github.com/SuneelFreimuth/vela
Author: Suneel Freimuth
Author-email: suneelfreimuth1@gmail.com
License: UNKNOWN
Project-URL: Bug Tracker, https://github.com/SuneelFreimuth/vela/issues
Platform: UNKNOWN
Classifier: Programming Language :: Python :: 3
Classifier: License :: OSI Approved :: MIT License
Classifier: Operating System :: OS Independent
Requires-Python: >=3.6
